{
  "chapter": 17,
  "chinese_name": "太上下知有之",
  "japanese_name": "最上の治者は、民がその存在を知るだけ",
  "summary": "最高のリーダーは存在感がなく、民が「自然にこうなった」と感じる統治をする。",
  "verses": [
    {
      "number": 1,
      "original": "太上，下知有之；其次，親而譽之；其次，畏之；其次，侮之。信不足，焉有不信焉。悠兮，其貴言。功成事遂，百姓皆謂我自然。",
      "modern_ja": "最上の治者は、民がその存在を知るだけ。その次は、民が親しみ称賛する。その次は、民が恐れる。その次は、民が侮る。信が足りなければ、不信が生まれる。悠然としてことばを大切にする。功が成り事が遂げられると、百姓は皆「自然にこうなった」と言う。",
      "english": "The best leader is barely known to the people. Next is one who is loved and praised. Next, one who is feared. Worst, one who is despised. When trust is lacking, distrust arises. The best leader speaks sparingly. When the work is done, the people say: 'We did it ourselves.'",
      "laozi": "一番いいリーダーは、いるかいないかわからない奴。次は好かれる奴。その次は怖がられる奴。最悪は、バカにされる奴。本当にすごい奴は、何も言わない。終わった後、みんなが「自分たちでやった」って言う…それが最上だ。名前なんか残らなくていい。",
      "keywords": [
        "太上",
        "自然",
        "貴言",
        "信"
      ]
    }
  ]
}
