{
  "chapter": 24,
  "chinese_name": "企者不立",
  "japanese_name": "つま先立ちは続かない",
  "summary": "背伸びや自己顕示は道に反する余計な行為であり、長続きしない。",
  "verses": [
    {
      "number": 1,
      "original": "企者不立；跨者不行；自見者不明；自是者不彰；自伐者無功；自矜者不長。其在道也，曰：餘食贅行。物或惡之，故有道者不處。",
      "modern_ja": "つま先立つ者は立ち続けられない。大股で歩く者は遠くへ行けない。自ら見せびらかす者は明らかでなく、自ら正しいとする者は彰かでなく、自ら誇る者は功なく、自ら驕る者は長続きしない。道からすればこれは余った食べ物、余計な行い。万物もこれを嫌う。だから道ある者はそこにとどまらない。",
      "english": "He who stands on tiptoe cannot stand firm. He who strides cannot walk far. He who shows off is not illuminated. He who is self-righteous is not distinguished. He who boasts has no merit. He who is arrogant does not endure. From the standpoint of the Dao, these are like leftover food and excess baggage—all things detest them. Therefore one who has the Dao does not dwell there.",
      "laozi": "つま先立ちしてみろ。どれだけ持つ？ 大股で走ってみろ。すぐ疲れるだろ。見せびらかすやつ、自慢するやつ。道から見れば、食い残しだ…みんな嫌がる。道を知ってるやつは、そんなところにいない。",
      "keywords": [
        "企",
        "自見",
        "自伐",
        "余食贅行",
        "道"
      ]
    }
  ]
}
