{
  "chapter": 33,
  "chinese_name": "知人者智",
  "japanese_name": "自分を知る者こそ明",
  "summary": "他人を知るのは智だが、自分を知るのが真の明であり、自分に勝つ者こそ強い。",
  "verses": [
    {
      "number": 1,
      "original": "知人者智，自知者明。勝人者有力，自勝者強。知足者富。強行者有志。不失其所者久。死而不亡者壽。",
      "modern_ja": "他人を知る者は智であり、自分を知る者は明である。他人に勝つ者は力があり、自分に勝つ者は真に強い。足ることを知る者は富み、努力して行う者は志がある。その場所を失わない者は長く続き、死しても亡びない者は長寿である。",
      "english": "He who knows others is wise; he who knows himself is enlightened. He who conquers others has power; he who conquers himself is strong. He who knows contentment is rich. He who acts with determination has will. He who does not lose his place endures long. He who dies but does not perish has longevity.",
      "laozi": "人を見抜くのは、まあ賢い。でもな、自分を知ってるか？ それが本物だ。他人に勝つのは力だ。自分に勝つのが、本当の強さだ。足りてると思えれば、もう富んでる…死んでも残るものがある。それが、本当の長生きだ。",
      "keywords": [
        "自知",
        "自勝",
        "知足",
        "明",
        "壽"
      ]
    }
  ]
}
